pytest_maybe_raises.py
pytest_maybe_raises-0.1.1.dist-info/LICENSE
pytest_maybe_raises-0.1.1.dist-info/METADATA
pytest_maybe_raises-0.1.1.dist-info/WHEEL
pytest_maybe_raises-0.1.1.dist-info/entry_points.txt
pytest_maybe_raises-0.1.1.dist-info/top_level.txt
pytest_maybe_raises-0.1.1.dist-info/RECORD
