Metadata-Version: 2.1
Name: pytest-maybe-raises
Version: 0.1.1
Summary: Pytest fixture for optional exception testing.
Home-page: https://github.com/mondeja/pytest-maybe-raises
Author: Álvaro Mondéjar Rubio
Author-email: mondejar1994@gmail.com
License: BSD-3-Clause
Project-URL: Documentation, https://github.com/mondeja/pytest-maybe-raises#documentation
Project-URL: GitHub Project, https://github.com/mondeja/pytest-maybe-raises
Project-URL: Issue Tracker, https://github.com/mondeja/pytest-maybe-raises/issues
Platform: UNKNOWN
Classifier: Framework :: Pytest
Classifier: License :: OSI Approved :: BSD License
Classifier: Programming Language :: Python
Classifier: Programming Language :: Python :: 3
Classifier: Programming Language :: Python :: 3 :: Only
Classifier: Programming Language :: Python :: 3.6
Classifier: Programming Language :: Python :: 3.7
Classifier: Programming Language :: Python :: 3.8
Classifier: Programming Language :: Python :: 3.9
Classifier: Programming Language :: Python :: 3.10
Requires-Python: >=3.6
License-File: LICENSE
Provides-Extra: dev
Requires-Dist: black (==22.3.0) ; extra == 'dev'
Requires-Dist: bump2version (==1.0.1) ; extra == 'dev'
Requires-Dist: flake8 (==4.0.1) ; extra == 'dev'
Requires-Dist: flake8-implicit-str-concat (==0.3.0) ; extra == 'dev'
Requires-Dist: flake8-print (==5.0.0) ; extra == 'dev'
Requires-Dist: isort (==5.10.1) ; extra == 'dev'
Requires-Dist: pre-commit (==2.19.0) ; extra == 'dev'
Requires-Dist: pytest ; extra == 'dev'
Requires-Dist: yamllint (==1.26.3) ; extra == 'dev'
Provides-Extra: lint
Requires-Dist: black (==22.3.0) ; extra == 'lint'
Requires-Dist: flake8 (==4.0.1) ; extra == 'lint'
Requires-Dist: flake8-implicit-str-concat (==0.3.0) ; extra == 'lint'
Requires-Dist: flake8-print (==5.0.0) ; extra == 'lint'
Requires-Dist: isort (==5.10.1) ; extra == 'lint'
Requires-Dist: yamllint (==1.26.3) ; extra == 'lint'
Provides-Extra: test
Requires-Dist: pytest ; extra == 'test'
